alphatims/__init__.py
alphatims/__main__.py
alphatims/bruker.py
alphatims/cli.py
alphatims/compiling.py
alphatims/dia_data.py
alphatims/gui.py
alphatims/plotting.py
alphatims/tempmmap.py
alphatims/utils.py
alphatims/docs/cli_manual.pdf
alphatims/docs/gui_manual.pdf
alphatims/ext/timsdata.dll
alphatims/ext/timsdata.so
alphatims/img/github.png
alphatims/img/max-planck-gesellschaft.jpg
alphatims/img/mpi_logo.png
alphatims/lib/interface_parameters.json
docs/conf.py
release/pyinstaller/alphatims_pyinstaller.py
requirements/requirements.txt
requirements/requirements_development.txt
requirements/requirements_legacy.txt
requirements/requirements_legacy_loose.txt
requirements/requirements_loose.txt
requirements/requirements_plotting.txt
requirements/requirements_plotting_loose.txt
tests/test_bruker.py
tests/test_utils.py
alphatims-1.0.9.dist-info/LICENSE-THIRD-PARTY.txt
alphatims-1.0.9.dist-info/LICENSE.txt
alphatims-1.0.9.dist-info/METADATA
alphatims-1.0.9.dist-info/WHEEL
alphatims-1.0.9.dist-info/entry_points.txt
alphatims-1.0.9.dist-info/top_level.txt
alphatims-1.0.9.dist-info/RECORD
