Metadata-Version: 2.1
Name: alphatims
Version: 1.0.9
Author-email: Sander Willems <opensource@alphapept.com>, Eugenia Voytik <opensource@alphapept.com>
License: Apache License
Project-URL: Mann Labs Homepage, https://www.biochem.mpg.de/mann
Project-URL: Repository, https://github.com/MannLabs/alphatims
Project-URL: Documentation, https://alphatims.readthedocs.io/en/latest/
Project-URL: PyPi, https://pypi.org/project/alphatims/
Project-URL: Scientific paper, https://doi.org/10.1016/j.mcpro.2021.100149
Project-URL: Issues, https://github.com/MannLabs/alphatims/issues
Keywords: ms,mass spectrometry,bruker,timsTOF,proteomics,bioinformatics,data indexing,AlphaPept ecosystem
Classifier: Development Status :: 5 - Production/Stable
Classifier: Intended Audience :: Science/Research
Classifier: License :: OSI Approved :: Apache Software License
Classifier: Operating System :: OS Independent
Classifier: Programming Language :: Python :: 3.8
Classifier: Programming Language :: Python :: 3.9
Classifier: Programming Language :: Python :: 3.10
Classifier: Topic :: Scientific/Engineering :: Bio-Informatics
Requires-Python: >=3.8
License-File: LICENSE-THIRD-PARTY.txt
License-File: LICENSE.txt
Requires-Dist: click
Requires-Dist: h5py
Requires-Dist: numba
Requires-Dist: pandas
Requires-Dist: psutil
Requires-Dist: pyzstd
Requires-Dist: tqdm
Provides-Extra: development
Requires-Dist: jupyter ; extra == 'development'
Requires-Dist: jupyter-contrib-nbextensions ; extra == 'development'
Requires-Dist: pyinstaller ; extra == 'development'
Requires-Dist: autodocsumm ; extra == 'development'
Requires-Dist: sphinx-rtd-theme ; extra == 'development'
Requires-Dist: plotly ; extra == 'development'
Requires-Dist: seaborn ; extra == 'development'
Requires-Dist: twine ; extra == 'development'
Requires-Dist: bumpversion ; extra == 'development'
Requires-Dist: pywin32 ; (sys_platform == "win32") and extra == 'development'
Provides-Extra: legacy
Requires-Dist: python-lzf ; extra == 'legacy'
Provides-Extra: legacy-stable
Requires-Dist: python-lzf ==0.2.4 ; extra == 'legacy-stable'
Provides-Extra: plotting
Requires-Dist: bokeh ; extra == 'plotting'
Requires-Dist: datashader ; extra == 'plotting'
Requires-Dist: hvplot ; extra == 'plotting'
Requires-Dist: selenium ; extra == 'plotting'
Requires-Dist: jinja2 ; extra == 'plotting'
Provides-Extra: plotting-stable
Requires-Dist: bokeh ==2.2.3 ; extra == 'plotting-stable'
Requires-Dist: datashader ==0.12.1 ; extra == 'plotting-stable'
Requires-Dist: hvplot ==0.7.1 ; extra == 'plotting-stable'
Requires-Dist: selenium ==3.141.0 ; extra == 'plotting-stable'
Requires-Dist: jinja2 ==3.0.2 ; extra == 'plotting-stable'
Provides-Extra: stable
Requires-Dist: click ==8.1.3 ; extra == 'stable'
Requires-Dist: h5py ==3.8.0 ; extra == 'stable'
Requires-Dist: numba ==0.56.4 ; extra == 'stable'
Requires-Dist: pandas ==1.5.3 ; extra == 'stable'
Requires-Dist: psutil ==5.9.4 ; extra == 'stable'
Requires-Dist: pyzstd ==0.15.3 ; extra == 'stable'
Requires-Dist: tqdm ==4.64.1 ; extra == 'stable'
